purem/__init__.py
purem/core.py
purem/env_config.py
purem/file_structure.py
purem/loader.py
purem/logger.py
purem/utils.py
purem-3.0.6.dist-info/licenses/LICENSE
purem-3.0.6.dist-info/METADATA
purem-3.0.6.dist-info/WHEEL
purem-3.0.6.dist-info/top_level.txt
purem-3.0.6.dist-info/RECORD
