Metadata-Version: 2.4
Name: purem
Version: 3.0.6
Summary: The official high-performance mapping function for mixed-type arrays powered by Work TIF Ltd.
Author-email: Raman Marozau <raman@worktif.com>
License-Expression: BUSL-1.1
Project-URL: Homepage, https://github.com/worktif/purem
Project-URL: Documentation, https://worktif.com/docs/basic-usage
Keywords: mapping,performance,numpy,arrays
Classifier: Typing :: Typed
Classifier: Programming Language :: Python :: 3 :: Only
Classifier: Programming Language :: Python :: 3.8
Classifier: Programming Language :: Python :: 3.9
Classifier: Programming Language :: Python :: 3.10
Classifier: Programming Language :: Python :: 3.11
Classifier: Programming Language :: Python :: 3.12
Classifier: Programming Language :: Python :: 3.13
Classifier: Operating System :: OS Independent
Classifier: Operating System :: MacOS
Classifier: Operating System :: Unix
Classifier: Operating System :: POSIX
Classifier: Operating System :: POSIX :: Linux
Classifier: Operating System :: Microsoft :: Windows
Requires-Python: >=3.8
License-File: LICENSE
Requires-Dist: numpy~=2.1.3
Requires-Dist: numba~=0.61.0
Requires-Dist: certifi~=2025.1.31
Requires-Dist: pydantic~=2.10.6
Requires-Dist: dotenv~=0.9.9
Requires-Dist: python-dotenv~=1.1.0
Requires-Dist: setuptools~=65.5.1
Requires-Dist: requests~=2.32.3
Requires-Dist: pytest~=8.3.5
Requires-Dist: pytest-env~=1.1.5
Provides-Extra: dev
Requires-Dist: pytest; extra == "dev"
Requires-Dist: flake8; extra == "dev"
Requires-Dist: black; extra == "dev"
Requires-Dist: coverage; extra == "dev"
Requires-Dist: pytest-mock; extra == "dev"
Dynamic: license-file
